LICENSE
MANIFEST.in
README
setup.py
sleipnir.marshals.tsplib.egg-info/PKG-INFO
sleipnir.marshals.tsplib.egg-info/SOURCES.txt
sleipnir.marshals.tsplib.egg-info/dependency_links.txt
sleipnir.marshals.tsplib.egg-info/entry_points.txt
sleipnir.marshals.tsplib.egg-info/not-zip-safe
sleipnir.marshals.tsplib.egg-info/requires.txt
sleipnir.marshals.tsplib.egg-info/top_level.txt
tests/__init__.py
tests/test_marshal.py
tsplib/__init__.py
tsplib/constants.py
tsplib/marshal.py
tsplib/parser.py
tsplib/visitor.py