Metadata-Version: 1.0
Name: sleipnir.marshals.tsplib
Version: 0.1rc1
Summary: A TSPLib compatible serializer
Home-page: http://sleipnir.liberalia.net/
Author: Carlos Martín
Author-email: cmartin@liberalia.net
License: GNU General Public License, version 2
Platform: UNKNOWN
Classifier: Development Status :: 4 - Beta
Classifier: License :: OSI Approved :: GNU General Public License (GPL)
Classifier: Operating System :: OS Independent
Classifier: Programming Language :: Python :: 2.6
Classifier: Programming Language :: Python :: 2.7
Classifier: Topic :: Software Development
